abundant/__init__.py
abundant-0.0.1.dist-info/METADATA
abundant-0.0.1.dist-info/WHEEL
abundant-0.0.1.dist-info/RECORD
