Metadata-Version: 2.3
Name: abundant
Version: 0.0.1
Summary: Abundant SDK
Author: Jesse Hu
Requires-Python: >=3.8
